SimConf
