Metadata-Version: 2.1
Name: SimConf
Version: 0.1.6
Summary: Simple Attribute saving manager
Home-page: https://github.com/bokonV2/SimConf
Author: bokonV2
Author-email: bokon2014@yandex.ru
License: UNKNOWN
Project-URL: Bug Reports, https://github.com/bokonV2/SimConf/issues
Project-URL: Source, https://github.com/bokonV2/SimConf
Platform: UNKNOWN
Classifier: Intended Audience :: Developers
Classifier: Topic :: Software Development :: Build Tools
Classifier: License :: OSI Approved :: MIT License
Classifier: Programming Language :: Python :: 3
Classifier: Programming Language :: Python :: 3.6
Classifier: Programming Language :: Python :: 3.7
Classifier: Programming Language :: Python :: 3.8
Classifier: Programming Language :: Python :: 3.9
Classifier: Programming Language :: Python :: 3 :: Only
Requires-Python: >=3.6, <4
